bead_state_model/__init__.py
bead_state_model/base_setup_handler.py
bead_state_model/components.py
bead_state_model/data_reader.py
bead_state_model/filament_handler.py
bead_state_model/periodic_boundaries.py
bead_state_model/simulation.py
bead_state_model/system_setup.py
bead_state_model/network_assembly/__init__.py
bead_state_model/network_assembly/create_filament.py
bead_state_model/network_assembly/create_network.py
bead_state_model/network_assembly/create_network_natural.py
bead_state_model/network_assembly/create_network_simple.py
bead_state_model-2.3.2.dist-info/LICENSE
bead_state_model-2.3.2.dist-info/METADATA
bead_state_model-2.3.2.dist-info/WHEEL
bead_state_model-2.3.2.dist-info/top_level.txt
bead_state_model-2.3.2.dist-info/RECORD
